LICENSE
README.md
setup.py
oldmill/__init__.py
oldmillheater.egg-info/PKG-INFO
oldmillheater.egg-info/SOURCES.txt
oldmillheater.egg-info/dependency_links.txt
oldmillheater.egg-info/requires.txt
oldmillheater.egg-info/top_level.txt