Metadata-Version: 2.1
Name: oldmillheater
Version: 0.10.0
Summary: A python3 library to communicate with Mill
Home-page: https://github.com/alchemistake/oldpymill
Author: Daniel Hjelseth Hoyer
Author-email: mail@dahoiv.net
License: MIT
Classifier: Intended Audience :: Developers
Classifier: Operating System :: OS Independent
Classifier: Programming Language :: Python
Classifier: Programming Language :: Python :: 3
Classifier: Topic :: Home Automation
Classifier: Topic :: Software Development :: Libraries :: Python Modules
Requires-Python: >=3.5.3
License-File: LICENSE
